Metadata-Version: 2.1
Name: primelibpy
Version: 1.5
Summary: This library can be used in cryptoanalysis and some compatitive exams. It cover many different types of prime number and three factorization algorithems. This library also helps to generate random spacific type of prime number with desire digits. To use this library you mast have python 3.x
Home-page: https://github.com/mit1280/primelibpy
Author: MIT
Author-email: mitbpatel0128@gmail.com
License: UNKNOWN
Platform: UNKNOWN
Classifier: Intended Audience :: Developers
Classifier: Topic :: Software Development :: Build Tools
Classifier: License :: OSI Approved :: MIT License
Classifier: Programming Language :: Python :: 3
Classifier: Programming Language :: Python :: 3.4
Classifier: Programming Language :: Python :: 3.5
Classifier: Programming Language :: Python :: 3.6
Requires-Python: >=3.0
